[
    {
        "station_name": "Tel Aviv",
        "api_id": 123456789,
        "station_id": 9876654321,
        "station_type": 1,
        "lat": 32.070059,
        "alt": 34.826316
    },
    {
        "station_name": "Jerusalem",
        "api_id": 987654321,
        "station_id": 1234567890,
        "station_type": 1,
        "lat": 31.768319,
        "alt": 35.21371
    },
    {
        "station_name": "Haifa",
        "api_id": 567891234,
        "station_id": 5432167890,
        "station_type": 1,
        "lat": 32.794044,
        "alt": 34.989571
    },
    {
        "station_name": "Eilat",
        "api_id": 901234567,
        "station_id": 6789012345,
        "station_type": 1,
        "lat": 29.55805,
        "alt": 34.94821
    },
    {
        "station_name": "Dead Sea",
        "api_id": 345678901,
        "station_id": 2109876543,
        "station_type": 1,
        "lat": 31.525,
        "alt": 35.494
    }

]